{"section":"Effect Lifecycle","testNames":["#35 effect runs callback immediately on creation","#36 effect re-runs when dependency changes","#38 effect cleanup fn called before each re-run","#39 effect cleanup fn called on disposal","#40 effect cleanup runs outside reactive evaluation context","#42 effect not executed if disposed during pending batch","#108 effect self-dispose during execution is safe","#110 double-dispose is safe","#111 cleanup-triggered dispose prevents re-run","#141 dispose during execution then continue: no re-run","#143 destroyed effect not re-scheduled on later updates","#178 dispose cleanup reads don't leak to parent tracking context","#214 parent disposes and recreates child: downstream sees correct value","#201 computed-triggered disposal: effect skipped and no subscription leak","#202 computed-triggered disposal: sibling effects still notified","#203 computed disposal with unchanged-value sibling computed","#216 effects fire in creation order on shared signal","#217 new effect after dispose works normally","#222 effect created inside cleanup tracks its own deps","#229 cleanup reads computed: sees fresh value","#230 cleanup writes signal inside batch propagates after flush","#231 untracked inside cleanup: still no tracking","#233 cleanup write then read of dependent computed: sees new value","#235 batch inside effect body coalesces writes","#236 cleanup write to own dep: bounded recursion completes","#237 cleanup ordering on outer re-run: outer-cleanup before re-run, inner before outer if cascaded","#238 cleanup ordering on dispose: inner before outer if cascaded","#241 three-level cleanup ordering: deepest first if cascaded","#242 effect in computed: old inner cleanup (if any) before new eval","#243 cleanup ordering correct after prior inner-only re-run"],"results":{"lite-signal":{"#35 effect runs callback immediately on creation":"✅","#36 effect re-runs when dependency changes":"✅","#38 effect cleanup fn called before each re-run":"✅","#39 effect cleanup fn called on disposal":"✅","#40 effect cleanup runs outside reactive evaluation context":"✅","#42 effect not executed if disposed during pending batch":"✅","#108 effect self-dispose during execution is safe":"✅","#110 double-dispose is safe":"✅","#111 cleanup-triggered dispose prevents re-run":"✅","#141 dispose during execution then continue: no re-run":"✅","#143 destroyed effect not re-scheduled on later updates":"✅","#178 dispose cleanup reads don't leak to parent tracking context":"✅","#214 parent disposes and recreates child: downstream sees correct value":"✅","#201 computed-triggered disposal: effect skipped and no subscription leak":"✅","#202 computed-triggered disposal: sibling effects still notified":"✅","#203 computed disposal with unchanged-value sibling computed":"✅","#216 effects fire in creation order on shared signal":"✅","#217 new effect after dispose works normally":"✅","#222 effect created inside cleanup tracks its own deps":"✅","#229 cleanup reads computed: sees fresh value":"✅","#230 cleanup writes signal inside batch propagates after flush":"✅","#231 untracked inside cleanup: still no tracking":"✅","#233 cleanup write then read of dependent computed: sees new value":"✅","#235 batch inside effect body coalesces writes":"✅","#236 cleanup write to own dep: bounded recursion completes":"✅","#237 cleanup ordering on outer re-run: outer-cleanup before re-run, inner before outer if cascaded":"✅","#238 cleanup ordering on dispose: inner before outer if cascaded":"✅","#241 three-level cleanup ordering: deepest first if cascaded":"✅","#242 effect in computed: old inner cleanup (if any) before new eval":"✅","#243 cleanup ordering correct after prior inner-only re-run":"✅"},"alien-signals":{"#35 effect runs callback immediately on creation":"✅","#36 effect re-runs when dependency changes":"✅","#38 effect cleanup fn called before each re-run":"✅","#39 effect cleanup fn called on disposal":"✅","#40 effect cleanup runs outside reactive evaluation context":"✅","#42 effect not executed if disposed during pending batch":"✅","#108 effect self-dispose during execution is safe":"✅","#110 double-dispose is safe":"✅","#111 cleanup-triggered dispose prevents re-run":"✅","#141 dispose during execution then continue: no re-run":"✅","#143 destroyed effect not re-scheduled on later updates":"✅","#178 dispose cleanup reads don't leak to parent tracking context":"✅","#214 parent disposes and recreates child: downstream sees correct value":"✅","#201 computed-triggered disposal: effect skipped and no subscription leak":"✅","#202 computed-triggered disposal: sibling effects still notified":"✅","#203 computed disposal with unchanged-value sibling computed":"✅","#216 effects fire in creation order on shared signal":"✅","#217 new effect after dispose works normally":"✅","#222 effect created inside cleanup tracks its own deps":"✅","#229 cleanup reads computed: sees fresh value":"✅","#230 cleanup writes signal inside batch propagates after flush":"✅","#231 untracked inside cleanup: still no tracking":"✅","#233 cleanup write then read of dependent computed: sees new value":"✅","#235 batch inside effect body coalesces writes":"✅","#236 cleanup write to own dep: bounded recursion completes":"✅","#237 cleanup ordering on outer re-run: outer-cleanup before re-run, inner before outer if cascaded":"✅","#238 cleanup ordering on dispose: inner before outer if cascaded":"✅","#241 three-level cleanup ordering: deepest first if cascaded":"✅","#242 effect in computed: old inner cleanup (if any) before new eval":"✅","#243 cleanup ordering correct after prior inner-only re-run":"✅"},"@preact/signals-core":{"#35 effect runs callback immediately on creation":"✅","#36 effect re-runs when dependency changes":"✅","#38 effect cleanup fn called before each re-run":"✅","#39 effect cleanup fn called on disposal":"✅","#40 effect cleanup runs outside reactive evaluation context":"✅","#42 effect not executed if disposed during pending batch":"✅","#108 effect self-dispose during execution is safe":"✅","#110 double-dispose is safe":"✅","#111 cleanup-triggered dispose prevents re-run":"✅","#141 dispose during execution then continue: no re-run":"✅","#143 destroyed effect not re-scheduled on later updates":"✅","#178 dispose cleanup reads don't leak to parent tracking context":"✅","#214 parent disposes and recreates child: downstream sees correct value":"✅","#201 computed-triggered disposal: effect skipped and no subscription leak":"✅","#202 computed-triggered disposal: sibling effects still notified":"✅","#203 computed disposal with unchanged-value sibling computed":"✅","#216 effects fire in creation order on shared signal":"✅","#217 new effect after dispose works normally":"✅","#222 effect created inside cleanup tracks its own deps":"✅","#229 cleanup reads computed: sees fresh value":"✅","#230 cleanup writes signal inside batch propagates after flush":"✅","#231 untracked inside cleanup: still no tracking":"✅","#233 cleanup write then read of dependent computed: sees new value":"✅","#235 batch inside effect body coalesces writes":"❌","#236 cleanup write to own dep: bounded recursion completes":"✅","#237 cleanup ordering on outer re-run: outer-cleanup before re-run, inner before outer if cascaded":"✅","#238 cleanup ordering on dispose: inner before outer if cascaded":"✅","#241 three-level cleanup ordering: deepest first if cascaded":"✅","#242 effect in computed: old inner cleanup (if any) before new eval":"✅","#243 cleanup ordering correct after prior inner-only re-run":"✅"},"@reactively/core":{"#35 effect runs callback immediately on creation":"✅","#36 effect re-runs when dependency changes":"✅","#38 effect cleanup fn called before each re-run":"⬜","#39 effect cleanup fn called on disposal":"⬜","#40 effect cleanup runs outside reactive evaluation context":"⬜","#42 effect not executed if disposed during pending batch":"⬜","#108 effect self-dispose during execution is safe":"✅","#110 double-dispose is safe":"⬜","#111 cleanup-triggered dispose prevents re-run":"⬜","#141 dispose during execution then continue: no re-run":"✅","#143 destroyed effect not re-scheduled on later updates":"✅","#178 dispose cleanup reads don't leak to parent tracking context":"⬜","#214 parent disposes and recreates child: downstream sees correct value":"✅","#201 computed-triggered disposal: effect skipped and no subscription leak":"❌","#202 computed-triggered disposal: sibling effects still notified":"✅","#203 computed disposal with unchanged-value sibling computed":"✅","#216 effects fire in creation order on shared signal":"✅","#217 new effect after dispose works normally":"✅","#222 effect created inside cleanup tracks its own deps":"⬜","#229 cleanup reads computed: sees fresh value":"⬜","#230 cleanup writes signal inside batch propagates after flush":"⬜","#231 untracked inside cleanup: still no tracking":"⬜","#233 cleanup write then read of dependent computed: sees new value":"⬜","#235 batch inside effect body coalesces writes":"⬜","#236 cleanup write to own dep: bounded recursion completes":"⬜","#237 cleanup ordering on outer re-run: outer-cleanup before re-run, inner before outer if cascaded":"⬜","#238 cleanup ordering on dispose: inner before outer if cascaded":"⬜","#241 three-level cleanup ordering: deepest first if cascaded":"⬜","#242 effect in computed: old inner cleanup (if any) before new eval":"⬜","#243 cleanup ordering correct after prior inner-only re-run":"⬜"},"tansu":{"#35 effect runs callback immediately on creation":"✅","#36 effect re-runs when dependency changes":"✅","#38 effect cleanup fn called before each re-run":"⬜","#39 effect cleanup fn called on disposal":"⬜","#40 effect cleanup runs outside reactive evaluation context":"⬜","#42 effect not executed if disposed during pending batch":"✅","#108 effect self-dispose during execution is safe":"✅","#110 double-dispose is safe":"⬜","#111 cleanup-triggered dispose prevents re-run":"⬜","#141 dispose during execution then continue: no re-run":"✅","#143 destroyed effect not re-scheduled on later updates":"✅","#178 dispose cleanup reads don't leak to parent tracking context":"⬜","#214 parent disposes and recreates child: downstream sees correct value":"✅","#201 computed-triggered disposal: effect skipped and no subscription leak":"❌","#202 computed-triggered disposal: sibling effects still notified":"✅","#203 computed disposal with unchanged-value sibling computed":"✅","#216 effects fire in creation order on shared signal":"✅","#217 new effect after dispose works normally":"✅","#222 effect created inside cleanup tracks its own deps":"⬜","#229 cleanup reads computed: sees fresh value":"⬜","#230 cleanup writes signal inside batch propagates after flush":"⬜","#231 untracked inside cleanup: still no tracking":"⬜","#233 cleanup write then read of dependent computed: sees new value":"⬜","#235 batch inside effect body coalesces writes":"❌","#236 cleanup write to own dep: bounded recursion completes":"⬜","#237 cleanup ordering on outer re-run: outer-cleanup before re-run, inner before outer if cascaded":"⬜","#238 cleanup ordering on dispose: inner before outer if cascaded":"⬜","#241 three-level cleanup ordering: deepest first if cascaded":"⬜","#242 effect in computed: old inner cleanup (if any) before new eval":"⬜","#243 cleanup ordering correct after prior inner-only re-run":"⬜"},"signal-polyfill (TC39)":{"#35 effect runs callback immediately on creation":"✅","#36 effect re-runs when dependency changes":"✅","#38 effect cleanup fn called before each re-run":"✅","#39 effect cleanup fn called on disposal":"✅","#40 effect cleanup runs outside reactive evaluation context":"❌","#42 effect not executed if disposed during pending batch":"⬜","#108 effect self-dispose during execution is safe":"✅","#110 double-dispose is safe":"✅","#111 cleanup-triggered dispose prevents re-run":"✅","#141 dispose during execution then continue: no re-run":"✅","#143 destroyed effect not re-scheduled on later updates":"✅","#178 dispose cleanup reads don't leak to parent tracking context":"❌","#214 parent disposes and recreates child: downstream sees correct value":"✅","#201 computed-triggered disposal: effect skipped and no subscription leak":"❌","#202 computed-triggered disposal: sibling effects still notified":"✅","#203 computed disposal with unchanged-value sibling computed":"✅","#216 effects fire in creation order on shared signal":"✅","#217 new effect after dispose works normally":"✅","#222 effect created inside cleanup tracks its own deps":"✅","#229 cleanup reads computed: sees fresh value":"✅","#230 cleanup writes signal inside batch propagates after flush":"⬜","#231 untracked inside cleanup: still no tracking":"✅","#233 cleanup write then read of dependent computed: sees new value":"✅","#235 batch inside effect body coalesces writes":"⬜","#236 cleanup write to own dep: bounded recursion completes":"✅","#237 cleanup ordering on outer re-run: outer-cleanup before re-run, inner before outer if cascaded":"✅","#238 cleanup ordering on dispose: inner before outer if cascaded":"✅","#241 three-level cleanup ordering: deepest first if cascaded":"✅","#242 effect in computed: old inner cleanup (if any) before new eval":"✅","#243 cleanup ordering correct after prior inner-only re-run":"✅"},"@vue/reactivity":{"#35 effect runs callback immediately on creation":"✅","#36 effect re-runs when dependency changes":"✅","#38 effect cleanup fn called before each re-run":"✅","#39 effect cleanup fn called on disposal":"✅","#40 effect cleanup runs outside reactive evaluation context":"✅","#42 effect not executed if disposed during pending batch":"✅","#108 effect self-dispose during execution is safe":"✅","#110 double-dispose is safe":"✅","#111 cleanup-triggered dispose prevents re-run":"✅","#141 dispose during execution then continue: no re-run":"❌","#143 destroyed effect not re-scheduled on later updates":"✅","#178 dispose cleanup reads don't leak to parent tracking context":"✅","#214 parent disposes and recreates child: downstream sees correct value":"✅","#201 computed-triggered disposal: effect skipped and no subscription leak":"❌","#202 computed-triggered disposal: sibling effects still notified":"✅","#203 computed disposal with unchanged-value sibling computed":"✅","#216 effects fire in creation order on shared signal":"✅","#217 new effect after dispose works normally":"✅","#222 effect created inside cleanup tracks its own deps":"✅","#229 cleanup reads computed: sees fresh value":"✅","#230 cleanup writes signal inside batch propagates after flush":"✅","#231 untracked inside cleanup: still no tracking":"✅","#233 cleanup write then read of dependent computed: sees new value":"✅","#235 batch inside effect body coalesces writes":"✅","#236 cleanup write to own dep: bounded recursion completes":"✅","#237 cleanup ordering on outer re-run: outer-cleanup before re-run, inner before outer if cascaded":"✅","#238 cleanup ordering on dispose: inner before outer if cascaded":"✅","#241 three-level cleanup ordering: deepest first if cascaded":"✅","#242 effect in computed: old inner cleanup (if any) before new eval":"✅","#243 cleanup ordering correct after prior inner-only re-run":"✅"},"mobx":{"#35 effect runs callback immediately on creation":"✅","#36 effect re-runs when dependency changes":"✅","#38 effect cleanup fn called before each re-run":"⬜","#39 effect cleanup fn called on disposal":"⬜","#40 effect cleanup runs outside reactive evaluation context":"⬜","#42 effect not executed if disposed during pending batch":"✅","#108 effect self-dispose during execution is safe":"✅","#110 double-dispose is safe":"⬜","#111 cleanup-triggered dispose prevents re-run":"⬜","#141 dispose during execution then continue: no re-run":"✅","#143 destroyed effect not re-scheduled on later updates":"✅","#178 dispose cleanup reads don't leak to parent tracking context":"⬜","#214 parent disposes and recreates child: downstream sees correct value":"✅","#201 computed-triggered disposal: effect skipped and no subscription leak":"✅","#202 computed-triggered disposal: sibling effects still notified":"✅","#203 computed disposal with unchanged-value sibling computed":"✅","#216 effects fire in creation order on shared signal":"✅","#217 new effect after dispose works normally":"✅","#222 effect created inside cleanup tracks its own deps":"⬜","#229 cleanup reads computed: sees fresh value":"⬜","#230 cleanup writes signal inside batch propagates after flush":"⬜","#231 untracked inside cleanup: still no tracking":"⬜","#233 cleanup write then read of dependent computed: sees new value":"⬜","#235 batch inside effect body coalesces writes":"❌","#236 cleanup write to own dep: bounded recursion completes":"⬜","#237 cleanup ordering on outer re-run: outer-cleanup before re-run, inner before outer if cascaded":"⬜","#238 cleanup ordering on dispose: inner before outer if cascaded":"⬜","#241 three-level cleanup ordering: deepest first if cascaded":"⬜","#242 effect in computed: old inner cleanup (if any) before new eval":"⬜","#243 cleanup ordering correct after prior inner-only re-run":"⬜"},"@reatom/core":{"#35 effect runs callback immediately on creation":"✅","#36 effect re-runs when dependency changes":"✅","#38 effect cleanup fn called before each re-run":"✅","#39 effect cleanup fn called on disposal":"✅","#40 effect cleanup runs outside reactive evaluation context":"✅","#42 effect not executed if disposed during pending batch":"✅","#108 effect self-dispose during execution is safe":"✅","#110 double-dispose is safe":"✅","#111 cleanup-triggered dispose prevents re-run":"✅","#141 dispose during execution then continue: no re-run":"✅","#143 destroyed effect not re-scheduled on later updates":"✅","#178 dispose cleanup reads don't leak to parent tracking context":"✅","#214 parent disposes and recreates child: downstream sees correct value":"✅","#201 computed-triggered disposal: effect skipped and no subscription leak":"✅","#202 computed-triggered disposal: sibling effects still notified":"✅","#203 computed disposal with unchanged-value sibling computed":"✅","#216 effects fire in creation order on shared signal":"✅","#217 new effect after dispose works normally":"✅","#222 effect created inside cleanup tracks its own deps":"❌","#229 cleanup reads computed: sees fresh value":"✅","#230 cleanup writes signal inside batch propagates after flush":"✅","#231 untracked inside cleanup: still no tracking":"✅","#233 cleanup write then read of dependent computed: sees new value":"✅","#235 batch inside effect body coalesces writes":"❌","#236 cleanup write to own dep: bounded recursion completes":"✅","#237 cleanup ordering on outer re-run: outer-cleanup before re-run, inner before outer if cascaded":"✅","#238 cleanup ordering on dispose: inner before outer if cascaded":"✅","#241 three-level cleanup ordering: deepest first if cascaded":"✅","#242 effect in computed: old inner cleanup (if any) before new eval":"✅","#243 cleanup ordering correct after prior inner-only re-run":"✅"},"svelte":{"#35 effect runs callback immediately on creation":"✅","#36 effect re-runs when dependency changes":"✅","#38 effect cleanup fn called before each re-run":"✅","#39 effect cleanup fn called on disposal":"✅","#40 effect cleanup runs outside reactive evaluation context":"✅","#42 effect not executed if disposed during pending batch":"⬜","#108 effect self-dispose during execution is safe":"✅","#110 double-dispose is safe":"✅","#111 cleanup-triggered dispose prevents re-run":"❌","#141 dispose during execution then continue: no re-run":"✅","#143 destroyed effect not re-scheduled on later updates":"✅","#178 dispose cleanup reads don't leak to parent tracking context":"✅","#214 parent disposes and recreates child: downstream sees correct value":"✅","#201 computed-triggered disposal: effect skipped and no subscription leak":"✅","#202 computed-triggered disposal: sibling effects still notified":"❌","#203 computed disposal with unchanged-value sibling computed":"✅","#216 effects fire in creation order on shared signal":"✅","#217 new effect after dispose works normally":"✅","#222 effect created inside cleanup tracks its own deps":"✅","#229 cleanup reads computed: sees fresh value":"❌","#230 cleanup writes signal inside batch propagates after flush":"⬜","#231 untracked inside cleanup: still no tracking":"⬜","#233 cleanup write then read of dependent computed: sees new value":"✅","#235 batch inside effect body coalesces writes":"⬜","#236 cleanup write to own dep: bounded recursion completes":"✅","#237 cleanup ordering on outer re-run: outer-cleanup before re-run, inner before outer if cascaded":"✅","#238 cleanup ordering on dispose: inner before outer if cascaded":"✅","#241 three-level cleanup ordering: deepest first if cascaded":"✅","#242 effect in computed: old inner cleanup (if any) before new eval":"✅","#243 cleanup ordering correct after prior inner-only re-run":"✅"},"solid-js":{"#35 effect runs callback immediately on creation":"✅","#36 effect re-runs when dependency changes":"✅","#38 effect cleanup fn called before each re-run":"✅","#39 effect cleanup fn called on disposal":"✅","#40 effect cleanup runs outside reactive evaluation context":"✅","#42 effect not executed if disposed during pending batch":"✅","#108 effect self-dispose during execution is safe":"✅","#110 double-dispose is safe":"✅","#111 cleanup-triggered dispose prevents re-run":"❌","#141 dispose during execution then continue: no re-run":"❌","#143 destroyed effect not re-scheduled on later updates":"✅","#178 dispose cleanup reads don't leak to parent tracking context":"✅","#214 parent disposes and recreates child: downstream sees correct value":"✅","#201 computed-triggered disposal: effect skipped and no subscription leak":"✅","#202 computed-triggered disposal: sibling effects still notified":"✅","#203 computed disposal with unchanged-value sibling computed":"✅","#216 effects fire in creation order on shared signal":"❌","#217 new effect after dispose works normally":"✅","#222 effect created inside cleanup tracks its own deps":"✅","#229 cleanup reads computed: sees fresh value":"✅","#230 cleanup writes signal inside batch propagates after flush":"✅","#231 untracked inside cleanup: still no tracking":"✅","#233 cleanup write then read of dependent computed: sees new value":"✅","#235 batch inside effect body coalesces writes":"❌","#236 cleanup write to own dep: bounded recursion completes":"✅","#237 cleanup ordering on outer re-run: outer-cleanup before re-run, inner before outer if cascaded":"✅","#238 cleanup ordering on dispose: inner before outer if cascaded":"✅","#241 three-level cleanup ordering: deepest first if cascaded":"✅","#242 effect in computed: old inner cleanup (if any) before new eval":"✅","#243 cleanup ordering correct after prior inner-only re-run":"✅"},"@solidjs/signals":{"#35 effect runs callback immediately on creation":"✅","#36 effect re-runs when dependency changes":"✅","#38 effect cleanup fn called before each re-run":"⬜","#39 effect cleanup fn called on disposal":"⬜","#40 effect cleanup runs outside reactive evaluation context":"⬜","#42 effect not executed if disposed during pending batch":"✅","#108 effect self-dispose during execution is safe":"✅","#110 double-dispose is safe":"⬜","#111 cleanup-triggered dispose prevents re-run":"⬜","#141 dispose during execution then continue: no re-run":"✅","#143 destroyed effect not re-scheduled on later updates":"✅","#178 dispose cleanup reads don't leak to parent tracking context":"⬜","#214 parent disposes and recreates child: downstream sees correct value":"✅","#201 computed-triggered disposal: effect skipped and no subscription leak":"✅","#202 computed-triggered disposal: sibling effects still notified":"✅","#203 computed disposal with unchanged-value sibling computed":"✅","#216 effects fire in creation order on shared signal":"✅","#217 new effect after dispose works normally":"✅","#222 effect created inside cleanup tracks its own deps":"⬜","#229 cleanup reads computed: sees fresh value":"⬜","#230 cleanup writes signal inside batch propagates after flush":"⬜","#231 untracked inside cleanup: still no tracking":"⬜","#233 cleanup write then read of dependent computed: sees new value":"⬜","#235 batch inside effect body coalesces writes":"✅","#236 cleanup write to own dep: bounded recursion completes":"⬜","#237 cleanup ordering on outer re-run: outer-cleanup before re-run, inner before outer if cascaded":"⬜","#238 cleanup ordering on dispose: inner before outer if cascaded":"⬜","#241 three-level cleanup ordering: deepest first if cascaded":"⬜","#242 effect in computed: old inner cleanup (if any) before new eval":"⬜","#243 cleanup ordering correct after prior inner-only re-run":"⬜"},"S.js":{"#35 effect runs callback immediately on creation":"✅","#36 effect re-runs when dependency changes":"✅","#38 effect cleanup fn called before each re-run":"✅","#39 effect cleanup fn called on disposal":"✅","#40 effect cleanup runs outside reactive evaluation context":"❌","#42 effect not executed if disposed during pending batch":"❌","#108 effect self-dispose during execution is safe":"✅","#110 double-dispose is safe":"✅","#111 cleanup-triggered dispose prevents re-run":"✅","#141 dispose during execution then continue: no re-run":"✅","#143 destroyed effect not re-scheduled on later updates":"✅","#178 dispose cleanup reads don't leak to parent tracking context":"✅","#214 parent disposes and recreates child: downstream sees correct value":"✅","#201 computed-triggered disposal: effect skipped and no subscription leak":"❌","#202 computed-triggered disposal: sibling effects still notified":"✅","#203 computed disposal with unchanged-value sibling computed":"✅","#216 effects fire in creation order on shared signal":"✅","#217 new effect after dispose works normally":"✅","#222 effect created inside cleanup tracks its own deps":"✅","#229 cleanup reads computed: sees fresh value":"✅","#230 cleanup writes signal inside batch propagates after flush":"❌","#231 untracked inside cleanup: still no tracking":"✅","#233 cleanup write then read of dependent computed: sees new value":"❌","#235 batch inside effect body coalesces writes":"❌","#236 cleanup write to own dep: bounded recursion completes":"✅","#237 cleanup ordering on outer re-run: outer-cleanup before re-run, inner before outer if cascaded":"✅","#238 cleanup ordering on dispose: inner before outer if cascaded":"✅","#241 three-level cleanup ordering: deepest first if cascaded":"✅","#242 effect in computed: old inner cleanup (if any) before new eval":"✅","#243 cleanup ordering correct after prior inner-only re-run":"✅"},"pota":{"#35 effect runs callback immediately on creation":"✅","#36 effect re-runs when dependency changes":"❌","#38 effect cleanup fn called before each re-run":"❌","#39 effect cleanup fn called on disposal":"✅","#40 effect cleanup runs outside reactive evaluation context":"❌","#42 effect not executed if disposed during pending batch":"✅","#108 effect self-dispose during execution is safe":"❌","#110 double-dispose is safe":"✅","#111 cleanup-triggered dispose prevents re-run":"❌","#141 dispose during execution then continue: no re-run":"❌","#143 destroyed effect not re-scheduled on later updates":"✅","#178 dispose cleanup reads don't leak to parent tracking context":"❌","#214 parent disposes and recreates child: downstream sees correct value":"✅","#201 computed-triggered disposal: effect skipped and no subscription leak":"✅","#202 computed-triggered disposal: sibling effects still notified":"❌","#203 computed disposal with unchanged-value sibling computed":"✅","#216 effects fire in creation order on shared signal":"❌","#217 new effect after dispose works normally":"❌","#222 effect created inside cleanup tracks its own deps":"❌","#229 cleanup reads computed: sees fresh value":"❌","#230 cleanup writes signal inside batch propagates after flush":"❌","#231 untracked inside cleanup: still no tracking":"❌","#233 cleanup write then read of dependent computed: sees new value":"❌","#235 batch inside effect body coalesces writes":"❌","#236 cleanup write to own dep: bounded recursion completes":"✅","#237 cleanup ordering on outer re-run: outer-cleanup before re-run, inner before outer if cascaded":"❌","#238 cleanup ordering on dispose: inner before outer if cascaded":"✅","#241 three-level cleanup ordering: deepest first if cascaded":"✅","#242 effect in computed: old inner cleanup (if any) before new eval":"✅","#243 cleanup ordering correct after prior inner-only re-run":"❌"},"@angular/core":{"#35 effect runs callback immediately on creation":"✅","#36 effect re-runs when dependency changes":"✅","#38 effect cleanup fn called before each re-run":"✅","#39 effect cleanup fn called on disposal":"✅","#40 effect cleanup runs outside reactive evaluation context":"❌","#42 effect not executed if disposed during pending batch":"⬜","#108 effect self-dispose during execution is safe":"✅","#110 double-dispose is safe":"✅","#111 cleanup-triggered dispose prevents re-run":"❌","#141 dispose during execution then continue: no re-run":"✅","#143 destroyed effect not re-scheduled on later updates":"✅","#178 dispose cleanup reads don't leak to parent tracking context":"❌","#214 parent disposes and recreates child: downstream sees correct value":"✅","#201 computed-triggered disposal: effect skipped and no subscription leak":"❌","#202 computed-triggered disposal: sibling effects still notified":"❌","#203 computed disposal with unchanged-value sibling computed":"✅","#216 effects fire in creation order on shared signal":"✅","#217 new effect after dispose works normally":"✅","#222 effect created inside cleanup tracks its own deps":"✅","#229 cleanup reads computed: sees fresh value":"✅","#230 cleanup writes signal inside batch propagates after flush":"⬜","#231 untracked inside cleanup: still no tracking":"✅","#233 cleanup write then read of dependent computed: sees new value":"✅","#235 batch inside effect body coalesces writes":"⬜","#236 cleanup write to own dep: bounded recursion completes":"❌","#237 cleanup ordering on outer re-run: outer-cleanup before re-run, inner before outer if cascaded":"✅","#238 cleanup ordering on dispose: inner before outer if cascaded":"✅","#241 three-level cleanup ordering: deepest first if cascaded":"✅","#242 effect in computed: old inner cleanup (if any) before new eval":"✅","#243 cleanup ordering correct after prior inner-only re-run":"✅"},"anod":{"#35 effect runs callback immediately on creation":"✅","#36 effect re-runs when dependency changes":"✅","#38 effect cleanup fn called before each re-run":"✅","#39 effect cleanup fn called on disposal":"✅","#40 effect cleanup runs outside reactive evaluation context":"✅","#42 effect not executed if disposed during pending batch":"✅","#108 effect self-dispose during execution is safe":"✅","#110 double-dispose is safe":"✅","#111 cleanup-triggered dispose prevents re-run":"✅","#141 dispose during execution then continue: no re-run":"✅","#143 destroyed effect not re-scheduled on later updates":"✅","#178 dispose cleanup reads don't leak to parent tracking context":"✅","#214 parent disposes and recreates child: downstream sees correct value":"✅","#201 computed-triggered disposal: effect skipped and no subscription leak":"❌","#202 computed-triggered disposal: sibling effects still notified":"✅","#203 computed disposal with unchanged-value sibling computed":"✅","#216 effects fire in creation order on shared signal":"✅","#217 new effect after dispose works normally":"✅","#222 effect created inside cleanup tracks its own deps":"✅","#229 cleanup reads computed: sees fresh value":"✅","#230 cleanup writes signal inside batch propagates after flush":"✅","#231 untracked inside cleanup: still no tracking":"✅","#233 cleanup write then read of dependent computed: sees new value":"❌","#235 batch inside effect body coalesces writes":"❌","#236 cleanup write to own dep: bounded recursion completes":"✅","#237 cleanup ordering on outer re-run: outer-cleanup before re-run, inner before outer if cascaded":"❌","#238 cleanup ordering on dispose: inner before outer if cascaded":"❌","#241 three-level cleanup ordering: deepest first if cascaded":"❌","#242 effect in computed: old inner cleanup (if any) before new eval":"✅","#243 cleanup ordering correct after prior inner-only re-run":"❌"}}}